MANIFEST.in
README.rst
setup.cfg
setup.py
gist/__init__.py
gist/action.py
gist/commands.py
gist/endpoints.py
gist.egg-info/PKG-INFO
gist.egg-info/SOURCES.txt
gist.egg-info/dependency_links.txt
gist.egg-info/entry_points.txt
gist.egg-info/requires.txt
gist.egg-info/top_level.txt